lettercase/__init__.py
lettercase/detect.py
lettercase/letter_case.py
lettercase/tools.py
lettercase/converters/__init__.py
lettercase/converters/darwin_case.py
lettercase/converters/dromedary_case.py
lettercase/converters/pascal_case.py
lettercase/converters/screaming_snake_case.py
lettercase/converters/snake_case.py
lettercase-0.3.2.dist-info/LICENSE
lettercase-0.3.2.dist-info/METADATA
lettercase-0.3.2.dist-info/WHEEL
lettercase-0.3.2.dist-info/top_level.txt
lettercase-0.3.2.dist-info/RECORD
