Metadata-Version: 2.1
Name: lettercase
Version: 0.3.2
Summary: Detection and conversion between letter cases
Home-page: https://github.com/gieseladev/lettercase
Author: Giesela Inc.
Author-email: team@giesela.dev
License: UNKNOWN
Platform: UNKNOWN
Requires-Python: ~=3.7
